f5_openstack_lbaasv2_driver-10.1.0.dist-info/DESCRIPTION.rst
f5_openstack_lbaasv2_driver-10.1.0.dist-info/METADATA
f5_openstack_lbaasv2_driver-10.1.0.dist-info/RECORD
f5_openstack_lbaasv2_driver-10.1.0.dist-info/WHEEL
f5_openstack_lbaasv2_driver-10.1.0.dist-info/entry_points.txt
f5_openstack_lbaasv2_driver-10.1.0.dist-info/metadata.json
f5_openstack_lbaasv2_driver-10.1.0.dist-info/top_level.txt
f5lbaasdriver/__init__.py
f5lbaasdriver/test/__init__.py
f5lbaasdriver/test/tempest/__init__.py
f5lbaasdriver/test/tempest/config.py
f5lbaasdriver/test/tempest/plugin.py
f5lbaasdriver/test/tempest/services/__init__.py
f5lbaasdriver/test/tempest/services/clients/__init__.py
f5lbaasdriver/test/tempest/services/clients/bigip_client.py
f5lbaasdriver/test/tempest/services/clients/plugin_rpc_client.py
f5lbaasdriver/test/tempest/tests/__init__.py
f5lbaasdriver/test/tempest/tests/api/__init__.py
f5lbaasdriver/test/tempest/tests/api/base.py
f5lbaasdriver/test/tempest/tests/api/test_common_networks.py
f5lbaasdriver/test/tempest/tests/api/test_esd.py
f5lbaasdriver/test/tempest/tests/api/test_l7policy.py
f5lbaasdriver/test/tempest/tests/api/test_l7policy_rules.py
f5lbaasdriver/test/tempest/tests/api/test_l7policy_update.py
f5lbaasdriver/test/tempest/tests/api/test_load_balancers_admin.py
f5lbaasdriver/test/tempest/tests/api/test_member_status.py
f5lbaasdriver/test/tempest/tests/api/test_member_subnets.py
f5lbaasdriver/test/tempest/tests/api/test_pool_sync.py
f5lbaasdriver/test/tempest/tests/api/test_pools.py
f5lbaasdriver/test/tempest/tests/api/test_service_builder.py
f5lbaasdriver/test/tempest/tests/scenario/__init__.py
f5lbaasdriver/test/tempest/tests/scenario/f5_base.py
f5lbaasdriver/test/tempest/tests/scenario/test_esd.py
f5lbaasdriver/test/tempest/tests/scenario/test_l7policies_and_rules.py
f5lbaasdriver/test/tempest/tests/scenario/test_stats.py
f5lbaasdriver/utils/__init__.py
f5lbaasdriver/utils/add_environment.py
f5lbaasdriver/utils/environment_library.py
f5lbaasdriver/utils/remote_add_environment.py
f5lbaasdriver/utils/test/__init__.py
f5lbaasdriver/utils/test/test_environment_library.py
f5lbaasdriver/v2/__init__.py
f5lbaasdriver/v2/bigip/__init__.py
f5lbaasdriver/v2/bigip/agent_rpc.py
f5lbaasdriver/v2/bigip/agent_scheduler.py
f5lbaasdriver/v2/bigip/constants_v2.py
f5lbaasdriver/v2/bigip/disconnected_service.py
