Metadata-Version: 2.0
Name: f5-openstack-lbaasv2-driver
Version: 10.1.0
Summary: F5 Networks Driver for OpenStack LBaaSv2 service
Home-page: https://github.com/F5Networks/f5-openstack-lbaasv2-driver
Author: f5-openstack-lbaasv2-driver
Author-email: f5-openstack-lbaasv2-driver@f5.com
License: UNKNOWN
Platform: UNKNOWN
Classifier: Development Status :: 5 - Production/Stable
Classifier: License :: OSI Approved :: Apache Software License
Classifier: Operating System :: OS Independent
Classifier: Programming Language :: Python
Classifier: Intended Audience :: System Administrators
